[
    {
        "club_id": "1",
        "club_name": "Analytics Club",
        "manager_1_name": "Aryan Kashyap",
        "manager_1_position": "Manager",
        "manager_1_email": "manager.analytics.iitb@gmail.com",
        "manager_1_contact": "6206443759",
        "manager_1_linkedin": "https://www.linkedin.com/in/aryan-kshyp/",
        "manager_1_photo": "https://drive.google.com/file/d/1O2SmG9AI1FhFDnap2uoGdUEFdUVpQetG/view?usp=sharing",
        "manager_2_name": "",
        "manager_2_position": "",
        "manager_2_email": "",
        "manager_2_contact": "",
        "manager_2_linkedin": "",
        "manager_2_photo": ""
    },
    {
        "club_id": "2",
        "club_name": "Consult Club",
        "manager_1_name": "Anjali Jangid",
        "manager_1_position": "Manager",
        "manager_1_email": "manager.consultclub.iitb@gmail.com",
        "manager_1_contact": "8005540470",
        "manager_1_linkedin": "https://www.linkedin.com/in/anjali-jangid-68326229b/",
        "manager_1_photo": "https://drive.google.com/file/d/1pBqtEyCs8sx9m56eoedz2MTu6hiit795/view?usp=drivesdk",
        "manager_2_name": "",
        "manager_2_position": "",
        "manager_2_email": "",
        "manager_2_contact": "",
        "manager_2_linkedin": "",
        "manager_2_photo": ""
    },
    {
        "club_id": "3",
        "club_name": "Finance Club",
        "manager_1_name": "Kopal Goel",
        "manager_1_position": "Manager",
        "manager_1_email": "manager.finance.iitb@gmail.com",
        "manager_1_contact": "7022004676",
        "manager_1_linkedin": "https://www.linkedin.com/in/kopal-goel-010064294/",
        "manager_1_photo": "https://drive.google.com/file/d/1NBGgSKKS_dV975X_H1GT63NpV9FqmaTQ/view?usp=sharing",
        "manager_2_name": "Ritwik Raghav",
        "manager_2_position": "Manager",
        "manager_2_email": "manager.finance.iitb@gmail.com",
        "manager_2_contact": "",
        "manager_2_linkedin": "",
        "manager_2_photo": ""
    },
    {
        "club_id": "4",
        "club_name": "EnPoWER",
        "manager_1_name": "Rupanshi Vijayvargiya ",
        "manager_1_position": "ISAA and Head",
        "manager_1_email": "isaa.enpower.iitb@gmail.com",
        "manager_1_contact": "9301891196",
        "manager_1_linkedin": "https://www.linkedin.com/in/rupanshi-vijayvargiya-970a18287/",
        "manager_1_photo": "https://drive.google.com/open?id=1zurxS6WULRxjDBYuiMQuVrU2qjrQbTjD",
        "manager_2_name": "Dev Arora",
        "manager_2_position": "ISAA and Head",
        "manager_2_email": "isaa.enpower.iitb@gmail.com",
        "manager_2_contact": "8218705411",
        "manager_2_linkedin": "www.linkedin.com/in/dev-arora-b5857731b",
        "manager_2_photo": "https://drive.google.com/file/d/1DtmD5OOqeG1Y2msXgGcxoGjtKDZ2tpy-/view?usp=sharing"
    },
    {
        "club_id": "5",
        "club_name": "SSS",
        "manager_1_name": "Avani Gala",
        "manager_1_position": "ISAA and Head",
        "manager_1_email": "isaa.sss.iitb@gmail.com",
        "manager_1_contact": "8657424350",
        "manager_1_linkedin": "https://www.linkedin.com/in/avani-gala-ba12b0222/",
        "manager_1_photo": "https://drive.google.com/file/d/1DEGqUyjJZcmHcswr3T6oppF-z5le1Lf_/view?usp=sharing",
        "manager_2_name": "",
        "manager_2_position": "",
        "manager_2_email": "",
        "manager_2_contact": "",
        "manager_2_linkedin": "",
        "manager_2_photo": ""
    },
    {
        "club_id": "6",
        "club_name": "Career Cell",
        "manager_1_name": "Parv Khandelwal",
        "manager_1_position": "ISAA and Head",
        "manager_1_email": "isaa.careercell.iitb@gmail.com",
        "manager_1_contact": "8302649745",
        "manager_1_linkedin": "https://www.linkedin.com/in/parv-khandelwal-iitb/",
        "manager_1_photo": "https://drive.google.com/file/d/1wmXu-O8mBBBDp7jr5TN1BDVr9VvZfBGP/view?usp=sharing",
        "manager_2_name": "",
        "manager_2_position": "",
        "manager_2_email": "",
        "manager_2_contact": "",
        "manager_2_linkedin": "",
        "manager_2_photo": ""
    },
    {
        "club_id": "7",
        "club_name": "CCG",
        "manager_1_name": "Ved Parulekar",
        "manager_1_position": "President",
        "manager_1_email": "presidentccg1@gmail.com",
        "manager_1_contact": "9076120357",
        "manager_1_linkedin": "https://www.linkedin.com/in/ved-parulekar-8ab221283/",
        "manager_1_photo": "https://drive.google.com/file/d/1i4qhLn5DqPhuKiuh35W-1ErNPzgHKWoC/view?usp=sharing",
        "manager_2_name": "",
        "manager_2_position": "",
        "manager_2_email": "",
        "manager_2_contact": "",
        "manager_2_linkedin": "",
        "manager_2_photo": ""
    },
    {
        "club_id": "8",
        "club_name": "Investment Team",
        "manager_1_name": "Atharva Mittal",
        "manager_1_position": "Fund Manager",
        "manager_1_email": "investmentteam.ugac.iitb@gmail.com",
        "manager_1_contact": "9068810364",
        "manager_1_linkedin": "https://www.linkedin.com/in/atharva-mittal-374b74251/",
        "manager_1_photo": "https://drive.google.com/file/d/1gBsXfVEFshsrXfzduURfK43AzCL3k4b2/view?usp=sharing",
        "manager_2_name": "Aryan Tewari",
        "manager_2_position": "Principal",
        "manager_2_email": "investmentteam.ugac.iitb@gmail.com",
        "manager_2_contact": "9875408858",
        "manager_2_linkedin": "N/A",
        "manager_2_photo": ""
    },
    {
        "club_id": "9",
        "club_name": "DAV",
        "manager_1_name": "Aditya Anand Gupta",
        "manager_1_position": "Head",
        "manager_1_email": "heads.davteam@gmail.com",
        "manager_1_contact": "9324481748",
        "manager_1_linkedin": "https://www.linkedin.com/in/aditya-anand-gupta-3a7508299/",
        "manager_1_photo": "https://drive.google.com/file/d/1vOr2viZRy2b-zjpMF7Uh9EYlygpw_7n-/view?usp=sharing",
        "manager_2_name": "Prince Kumar",
        "manager_2_position": "Head",
        "manager_2_email": "heads.davteam@gmail.com",
        "manager_2_contact": "6203685770",
        "manager_2_linkedin": "https://www.linkedin.com/in/prince-kumar-880734270/",
        "manager_2_photo": "https://drive.google.com/file/d/1QNUHdJZ4616VQtu8d6m2p9OI9TZ2HGfR/view?usp=drivesdk"
    },
    {
        "club_id": "10",
        "club_name": "ISIR",
        "manager_1_name": "Parag Ingle",
        "manager_1_position": "ISIR",
        "manager_1_email": "isecir.iitb@gmail.com",
        "manager_1_contact": "7219335001",
        "manager_1_linkedin": "https://www.linkedin.com/in/parag-ingle-415941247",
        "manager_1_photo": "https://drive.google.com/open?id=1Xz01_Ykk_KjvtepxAzq5YNwl1UFsCX6x",
        "manager_2_name": "",
        "manager_2_position": "",
        "manager_2_email": "",
        "manager_2_contact": "",
        "manager_2_linkedin": "",
        "manager_2_photo": ""
    }
]